<?xml version="1.0" encoding="UTF-8" ?>
<!DOCTYPE tiles-definitions PUBLIC
        "-//Apache Software Foundation//DTD Tiles Configuration 3.0//EN"
        "http://tiles.apache.org/dtds/tiles-config_3_0.dtd">
<tiles-definitions>

    <definition name="default" template="/WEB-INF/tiles/layouts/default.jsp">
        <put-attribute name="header" value="/WEB-INF/tiles/templates/header.jsp"/>
        <put-attribute name="footer" value="/WEB-INF/tiles/templates/footer.jsp"/>
    </definition>

    <definition name="login" extends="default">
        <put-attribute name="title" value="Login"/>
        <put-attribute name="body" value="/WEB-INF/views/common/login.jsp"/>
    </definition>

    <definition name="registration" extends="default">
        <put-attribute name="title" value="Registration"/>
        <put-attribute name="body" value="/WEB-INF/views/common/registration.jsp"/>
    </definition>

    <definition name="createMessageDialog" extends="default">
        <put-attribute name="title" value="createMessageDialog"/>
        <put-attribute name="body" value="/WEB-INF/views/common/createMessageDialog.jsp"/>
    </definition>

    <definition name="showMessageDialog" extends="default">
        <put-attribute name="title" value="showMessageDialog"/>
        <put-attribute name="body" value="/WEB-INF/views/common/showMessageDialog.jsp"/>
    </definition>

    <definition name="piece_of_news" extends="default">
        <put-attribute name="title" value="piece_of_news"/>
        <put-attribute name="body" value="/WEB-INF/views/news/piece_of_news.jsp"/>
    </definition>

    <definition name="newLab" extends="default">
        <put-attribute name="title" value="newLab"/>
        <put-attribute name="body" value="/WEB-INF/views/labs/newLab.jsp"/>
    </definition>

    <definition name="compiler" extends="default">
        <put-attribute name="title" value="compiler"/>
        <put-attribute name="body" value="/WEB-INF/views/common/compiler.jsp"/>
    </definition>

</tiles-definitions>